opus_instrumenta/__init__.py
opus_instrumenta/molitor.py
opus_instrumenta/hooks/.gitkeep
opus_instrumenta/hooks/__init__.py
opus_instrumenta/hooks/kvs_hook.py
opus_instrumenta/persistence/.gitkeep
opus_instrumenta/task_processors/.gitkeep
opus_instrumenta/task_processors/__init__.py
opus_instrumenta/task_processors/cli_input_prompt_v1.py
opus_instrumenta/task_processors/shell_script_v1.py
opus_instrumenta/task_processors/web_download_file.py
opus_instrumenta-1.3.dist-info/METADATA
opus_instrumenta-1.3.dist-info/WHEEL
opus_instrumenta-1.3.dist-info/entry_points.txt
opus_instrumenta-1.3.dist-info/licenses/LICENSE
opus_instrumenta-1.3.dist-info/RECORD
