Metadata-Version: 2.1
Name: opus-instrumenta
Version: 1.3
Summary: Various implementations of hooks, processors and other classes from the main magnum-opus project.
Project-URL: Homepage, https://github.com/nicc777/opus-instrumenta
Project-URL: Documentation, https://github.com/nicc777/opus-instrumenta
Project-URL: Repository, https://github.com/nicc777/opus-instrumenta
Project-URL: Issues, https://github.com/nicc777/opus-instrumenta/issues
Project-URL: Changelog, https://raw.githubusercontent.com/nicc777/opus-instrumenta/main/CHANGELOG.md
Author-email: Nico Coetzee <nicc777@gmail.com>
Maintainer-email: Nico Coetzee <nicc777@gmail.com>
License: MIT License
License-File: LICENSE
Classifier: Development Status :: 3 - Alpha
Classifier: Intended Audience :: Developers
Classifier: License :: OSI Approved :: MIT License
Classifier: Programming Language :: Python :: 3
Classifier: Programming Language :: Python :: 3.8
Classifier: Programming Language :: Python :: 3.9
Classifier: Programming Language :: Python :: 3.10
Classifier: Programming Language :: Python :: 3.11
Classifier: Programming Language :: Python :: 3.12
Requires-Python: >=3.8
Requires-Dist: magnum-opus
Requires-Dist: opus-adstator
